torspray/__init__.py
torspray/torspray.py
torspray/modules/__init__.py
torspray/modules/classes.py
torspray/modules/config.py
torspray/modules/db.py
torspray/modules/node.py
torspray/modules/ssh_keys.py
torspray/modules/tui.py
torspray/sprays/__init__.py
torspray/sprays/debian_11_torbridge/__init__.py
torspray/sprays/debian_11_torbridge/spray.py
torspray-0.1.6.dist-info/LICENSE
torspray-0.1.6.dist-info/METADATA
torspray-0.1.6.dist-info/WHEEL
torspray-0.1.6.dist-info/entry_points.txt
torspray-0.1.6.dist-info/top_level.txt
torspray-0.1.6.dist-info/RECORD
